opal_mcp_adapter/README.md
opal_mcp_adapter/__init__.py
opal_mcp_adapter/cli.py
opal_mcp_adapter/server.py
opal_mcp_adapter/api/__init__.py
opal_mcp_adapter/api/routes.py
opal_mcp_adapter/clients/__init__.py
opal_mcp_adapter/clients/mcp_client.py
opal_mcp_adapter/config/__init__.py
opal_mcp_adapter/config/settings.py
opal_mcp_adapter/models/__init__.py
opal_mcp_adapter/models/adapter_state.py
opal_mcp_adapter/models/mcp_models.py
opal_mcp_adapter/models/tool_config.py
opal_mcp_adapter/services/__init__.py
opal_mcp_adapter/services/mcp_service.py
opal_mcp_adapter/utils/__init__.py
opal_mcp_adapter/utils/schema_converter.py
opal_mcp_adapter-0.0.4.dist-info/METADATA
opal_mcp_adapter-0.0.4.dist-info/WHEEL
opal_mcp_adapter-0.0.4.dist-info/entry_points.txt
opal_mcp_adapter-0.0.4.dist-info/top_level.txt
opal_mcp_adapter-0.0.4.dist-info/RECORD
