Metadata-Version: 2.4
Name: opal-mcp-adapter
Version: 0.0.4
Summary: Bidirectional adapter for converting between MCP and Opal tools
Requires-Python: >=3.10
Requires-Dist: fastapi>=0.104.0
Requires-Dist: httpx>=0.25.0
Requires-Dist: mcp>=1.9.4
Requires-Dist: optimizely-opal-opal-tools-sdk>=0.1.1.dev0
Requires-Dist: pydantic>=2.0.0
Requires-Dist: python-multipart>=0.0.6
Requires-Dist: pyyaml>=6.0.1
Requires-Dist: uvicorn>=0.24.0
Provides-Extra: dev
Requires-Dist: pytest>=7.0.0; extra == "dev"
Requires-Dist: pytest-asyncio>=0.21.0; extra == "dev"
Requires-Dist: httpx>=0.25.0; extra == "dev"
Dynamic: requires-python
